myhome/__init__.py
myhome/_aioadapter.py
myhome/_gen/__init__.py
myhome/_gen/api/__init__.py
myhome/_gen/api/default_api.py
myhome/_gen/api_client.py
myhome/_gen/configuration.py
myhome/_gen/exceptions.py
myhome/_gen/model/__init__.py
myhome/_gen/model/access_status.py
myhome/_gen/model/action.py
myhome/_gen/model/action_list.py
myhome/_gen/model/event.py
myhome/_gen/model/get_actual_user_response.py
myhome/_gen/model/get_role_user_response.py
myhome/_gen/model/init_check_response.py
myhome/_gen/model/login_request.py
myhome/_gen/model/login_response.py
myhome/_gen/model/object_info.py
myhome/_gen/model/object_list.py
myhome/_gen/model/object_value.py
myhome/_gen/model/object_value_dimmer.py
myhome/_gen/model/object_value_light.py
myhome/_gen/model/object_value_shutter.py
myhome/_gen/model/object_value_thermostat.py
myhome/_gen/model/room.py
myhome/_gen/model/room_list.py
myhome/_gen/model/serial_server.py
myhome/_gen/model/set_object_value_request.py
myhome/_gen/model/set_object_value_response.py
myhome/_gen/model/specific_object_request.py
myhome/_gen/model/system_info.py
myhome/_gen/model/zone.py
myhome/_gen/model/zone_list.py
myhome/_gen/model_utils.py
myhome/_gen/rest.py
myhome/client.py
myhome/exception.py
myhome/object/__init__.py
myhome/object/base.py
myhome/object/light.py
myhome/object/shutter.py
myhome/object/thermostat.py
myhome-0.3.0.dist-info/LICENSE.md
myhome-0.3.0.dist-info/WHEEL
myhome-0.3.0.dist-info/METADATA
myhome-0.3.0.dist-info/RECORD
