Metadata-Version: 2.1
Name: myhome
Version: 0.3.0
Summary: Python client library for interacting with Bticino MyHomeSERVER1
Home-page: https://github.com/speijnik/myhome
License: MIT
Author: Stephan Peijnik-Steinwender
Author-email: speijnik@gmail.com
Requires-Python: >=3.7,<4.0
Classifier: Development Status :: 3 - Alpha
Classifier: Intended Audience :: Developers
Classifier: License :: OSI Approved :: MIT License
Classifier: Operating System :: OS Independent
Classifier: Programming Language :: Python :: 3
Classifier: Programming Language :: Python :: 3.7
Classifier: Programming Language :: Python :: 3.8
Classifier: Programming Language :: Python :: 3.9
Classifier: Topic :: Home Automation
Requires-Dist: aiohttp (>=3.7.4,<4.0.0)
Requires-Dist: python-dateutil (>=2.8.2,<3.0.0)
Project-URL: Repository, https://github.com/speijnik/myhome
